{"children":[{"adcode":410702,"name":"红旗区","center":[113.878158,35.302684],"centroid":[113.965116,35.2755],"childrenNum":0,"level":"district","parent":{"adcode":410700},"subFeatureIndex":0,"acroutes":[100000,410000,410700]},{"adcode":410703,"name":"卫滨区","center":[113.866065,35.304905],"centroid":[113.845,35.276723],"childrenNum":0,"level":"district","parent":{"adcode":410700},"subFeatureIndex":1,"acroutes":[100000,410000,410700]},{"adcode":410704,"name":"凤泉区","center":[113.906712,35.379855],"centroid":[113.860242,35.385559],"childrenNum":0,"level":"district","parent":{"adcode":410700},"subFeatureIndex":2,"acroutes":[100000,410000,410700]},{"adcode":410711,"name":"牧野区","center":[113.89716,35.312974],"centroid":[113.908706,35.337932],"childrenNum":0,"level":"district","parent":{"adcode":410700},"subFeatureIndex":3,"acroutes":[100000,410000,410700]},{"adcode":410721,"name":"新乡县","center":[113.806186,35.190021],"centroid":[113.834287,35.202384],"childrenNum":0,"level":"district","parent":{"adcode":410700},"subFeatureIndex":4,"acroutes":[100000,410000,410700]},{"adcode":410724,"name":"获嘉县","center":[113.657249,35.261685],"centroid":[113.645007,35.196795],"childrenNum":0,"level":"district","parent":{"adcode":410700},"subFeatureIndex":5,"acroutes":[100000,410000,410700]},{"adcode":410725,"name":"原阳县","center":[113.965966,35.054001],"centroid":[113.950653,35.021904],"childrenNum":0,"level":"district","parent":{"adcode":410700},"subFeatureIndex":6,"acroutes":[100000,410000,410700]},{"adcode":410726,"name":"延津县","center":[114.200982,35.149515],"centroid":[114.237014,35.2724],"childrenNum":0,"level":"district","parent":{"adcode":410700},"subFeatureIndex":7,"acroutes":[100000,410000,410700]},{"adcode":410727,"name":"封丘县","center":[114.423405,35.04057],"centroid":[114.48416,35.033246],"childrenNum":0,"level":"district","parent":{"adcode":410700},"subFeatureIndex":8,"acroutes":[100000,410000,410700]},{"adcode":410781,"name":"卫辉市","center":[114.065855,35.404295],"centroid":[114.074478,35.49545],"childrenNum":0,"level":"district","parent":{"adcode":410700},"subFeatureIndex":9,"acroutes":[100000,410000,410700]},{"adcode":410782,"name":"辉县市","center":[113.802518,35.461318],"centroid":[113.681879,35.537251],"childrenNum":0,"level":"district","parent":{"adcode":410700},"subFeatureIndex":10,"acroutes":[100000,410000,410700]},{"adcode":410783,"name":"长垣市","center":[114.673807,35.19615],"centroid":[114.762943,35.212761],"childrenNum":0,"level":"district","parent":{"adcode":410700},"subFeatureIndex":11,"acroutes":[100000,410000,410700]}],"adcode":410700,"name":"新乡市","center":[113.883991,35.302616],"centroid":[114.095247,35.263966],"childrenNum":12,"level":"city","acroutes":[100000,410000],"parent":{"adcode":410000}}