{"children":[{"adcode":530102,"name":"五华区","center":[102.704412,25.042165],"centroid":[102.668802,25.164859],"childrenNum":0,"level":"district","parent":{"adcode":530100},"subFeatureIndex":0,"acroutes":[100000,530000,530100]},{"adcode":530103,"name":"盘龙区","center":[102.729044,25.070239],"centroid":[102.827207,25.266924],"childrenNum":0,"level":"district","parent":{"adcode":530100},"subFeatureIndex":1,"acroutes":[100000,530000,530100]},{"adcode":530111,"name":"官渡区","center":[102.723437,25.021211],"centroid":[102.886044,25.058335],"childrenNum":0,"level":"district","parent":{"adcode":530100},"subFeatureIndex":2,"acroutes":[100000,530000,530100]},{"adcode":530112,"name":"西山区","center":[102.705904,25.02436],"centroid":[102.557795,24.974944],"childrenNum":0,"level":"district","parent":{"adcode":530100},"subFeatureIndex":3,"acroutes":[100000,530000,530100]},{"adcode":530113,"name":"东川区","center":[103.182,26.08349],"centroid":[103.071677,26.134075],"childrenNum":0,"level":"district","parent":{"adcode":530100},"subFeatureIndex":4,"acroutes":[100000,530000,530100]},{"adcode":530114,"name":"呈贡区","center":[102.801382,24.889275],"centroid":[102.855526,24.864324],"childrenNum":0,"level":"district","parent":{"adcode":530100},"subFeatureIndex":5,"acroutes":[100000,530000,530100]},{"adcode":530115,"name":"晋宁区","center":[102.594987,24.666944],"centroid":[102.57727,24.607357],"childrenNum":0,"level":"district","parent":{"adcode":530100},"subFeatureIndex":6,"acroutes":[100000,530000,530100]},{"adcode":530124,"name":"富民县","center":[102.497888,25.219667],"centroid":[102.561496,25.360662],"childrenNum":0,"level":"district","parent":{"adcode":530100},"subFeatureIndex":7,"acroutes":[100000,530000,530100]},{"adcode":530125,"name":"宜良县","center":[103.145989,24.918215],"centroid":[103.192653,24.941304],"childrenNum":0,"level":"district","parent":{"adcode":530100},"subFeatureIndex":8,"acroutes":[100000,530000,530100]},{"adcode":530126,"name":"石林彝族自治县","center":[103.271962,24.754545],"centroid":[103.418596,24.740927],"childrenNum":0,"level":"district","parent":{"adcode":530100},"subFeatureIndex":9,"acroutes":[100000,530000,530100]},{"adcode":530127,"name":"嵩明县","center":[103.038777,25.335087],"centroid":[103.096579,25.295154],"childrenNum":0,"level":"district","parent":{"adcode":530100},"subFeatureIndex":10,"acroutes":[100000,530000,530100]},{"adcode":530128,"name":"禄劝彝族苗族自治县","center":[102.46905,25.556533],"centroid":[102.586627,25.937806],"childrenNum":0,"level":"district","parent":{"adcode":530100},"subFeatureIndex":11,"acroutes":[100000,530000,530100]},{"adcode":530129,"name":"寻甸回族彝族自治县","center":[103.257588,25.559474],"centroid":[103.121371,25.660614],"childrenNum":0,"level":"district","parent":{"adcode":530100},"subFeatureIndex":12,"acroutes":[100000,530000,530100]},{"adcode":530181,"name":"安宁市","center":[102.485544,24.921785],"centroid":[102.384499,24.844772],"childrenNum":0,"level":"district","parent":{"adcode":530100},"subFeatureIndex":13,"acroutes":[100000,530000,530100]}],"adcode":530100,"name":"昆明市","center":[102.712251,25.040609],"centroid":[102.87442,25.387092],"childrenNum":14,"level":"city","acroutes":[100000,530000],"parent":{"adcode":530000}}